cinderclient/__init__.py
cinderclient/_i18n.py
cinderclient/api_versions.py
cinderclient/base.py
cinderclient/client.py
cinderclient/exceptions.py
cinderclient/extension.py
cinderclient/shell.py
cinderclient/shell_utils.py
cinderclient/utils.py
cinderclient/version.py
cinderclient/apiclient/__init__.py
cinderclient/apiclient/base.py
cinderclient/apiclient/exceptions.py
cinderclient/contrib/__init__.py
cinderclient/contrib/noauth.py
cinderclient/tests/__init__.py
cinderclient/tests/functional/__init__.py
cinderclient/tests/functional/base.py
cinderclient/tests/functional/test_cli.py
cinderclient/tests/functional/test_readonly_cli.py
cinderclient/tests/functional/test_snapshot_create_cli.py
cinderclient/tests/functional/test_volume_create_cli.py
cinderclient/tests/functional/test_volume_extend_cli.py
cinderclient/tests/unit/__init__.py
cinderclient/tests/unit/fake_actions_module.py
cinderclient/tests/unit/fakes.py
cinderclient/tests/unit/test_api_versions.py
cinderclient/tests/unit/test_auth_plugins.py
cinderclient/tests/unit/test_base.py
cinderclient/tests/unit/test_client.py
cinderclient/tests/unit/test_exceptions.py
cinderclient/tests/unit/test_http.py
cinderclient/tests/unit/test_shell.py
cinderclient/tests/unit/test_utils.py
cinderclient/tests/unit/utils.py
cinderclient/tests/unit/fixture_data/__init__.py
cinderclient/tests/unit/fixture_data/availability_zones.py
cinderclient/tests/unit/fixture_data/base.py
cinderclient/tests/unit/fixture_data/client.py
cinderclient/tests/unit/fixture_data/keystone_client.py
cinderclient/tests/unit/fixture_data/snapshots.py
cinderclient/tests/unit/v2/__init__.py
cinderclient/tests/unit/v2/fakes.py
cinderclient/tests/unit/v2/test_auth.py
cinderclient/tests/unit/v2/test_availability_zone.py
cinderclient/tests/unit/v2/test_capabilities.py
cinderclient/tests/unit/v2/test_cgsnapshots.py
cinderclient/tests/unit/v2/test_consistencygroups.py
cinderclient/tests/unit/v2/test_limits.py
cinderclient/tests/unit/v2/test_pools.py
qh_python_cinderclient-0.1.0.dev1631.dist-info/AUTHORS
qh_python_cinderclient-0.1.0.dev1631.dist-info/LICENSE
qh_python_cinderclient-0.1.0.dev1631.dist-info/METADATA
qh_python_cinderclient-0.1.0.dev1631.dist-info/WHEEL
qh_python_cinderclient-0.1.0.dev1631.dist-info/entry_points.txt
qh_python_cinderclient-0.1.0.dev1631.dist-info/pbr.json
qh_python_cinderclient-0.1.0.dev1631.dist-info/top_level.txt
qh_python_cinderclient-0.1.0.dev1631.dist-info/RECORD
