Metadata-Version: 2.1
Name: qh-python-cinderclient
Version: 0.1.0.dev1631
Summary: OpenStack Block Storage API Client Library
Home-page: https://docs.openstack.org/python-cinderclient/latest/
Author: OpenStack
Author-email: openstack-discuss@lists.openstack.org
License: UNKNOWN
Platform: UNKNOWN
Classifier: Development Status :: 5 - Production/Stable
Classifier: Environment :: Console
Classifier: Environment :: OpenStack
Classifier: Intended Audience :: Information Technology
Classifier: Intended Audience :: System Administrators
Classifier: License :: OSI Approved :: Apache Software License
Classifier: Operating System :: POSIX :: Linux
Classifier: Programming Language :: Python
Classifier: Programming Language :: Python :: 2
Classifier: Programming Language :: Python :: 2.7
Classifier: Programming Language :: Python :: 3
Classifier: Programming Language :: Python :: 3.6
Classifier: Programming Language :: Python :: 3.7
Requires-Dist: pbr (!=2.1.0,>=2.0.0)
Requires-Dist: PrettyTable (<0.8,>=0.7.1)
Requires-Dist: keystoneauth1 (>=3.4.0)
Requires-Dist: simplejson (>=3.5.1)
Requires-Dist: Babel (!=2.4.0,>=2.3.4)
Requires-Dist: six (>=1.10.0)
Requires-Dist: oslo.i18n (>=3.15.3)
Requires-Dist: oslo.utils (>=3.33.0)
Requires-Dist: requests (!=2.20.0,>=2.14.2)
